smallbrowser/__init__.py
smallbrowser-0.2.1.dist-info/LICENSE
smallbrowser-0.2.1.dist-info/METADATA
smallbrowser-0.2.1.dist-info/WHEEL
smallbrowser-0.2.1.dist-info/top_level.txt
smallbrowser-0.2.1.dist-info/RECORD
